gcc7-0.0.9.data/purelib/gcc7/__init__.py
gcc7-0.0.9.data/purelib/gcc7/gcc_root/bin/cpp
gcc7-0.0.9.data/purelib/gcc7/gcc_root/bin/gcc
gcc7-0.0.9.data/purelib/gcc7/gcc_root/bin/gcc-ar
gcc7-0.0.9.data/purelib/gcc7/gcc_root/bin/gcc-nm
gcc7-0.0.9.data/purelib/gcc7/gcc_root/bin/gcc-ranlib
gcc7-0.0.9.data/purelib/gcc7/gcc_root/bin/gcov
gcc7-0.0.9.data/purelib/gcc7/gcc_root/bin/gcov-dump
gcc7-0.0.9.data/purelib/gcc7/gcc_root/bin/gcov-tool
gcc7-0.0.9.data/purelib/gcc7/gcc_root/bin/x86_64-apple-darwin15.6.0-gcc
gcc7-0.0.9.data/purelib/gcc7/gcc_root/bin/x86_64-apple-darwin15.6.0-gcc-7.4.0
gcc7-0.0.9.data/purelib/gcc7/gcc_root/bin/x86_64-apple-darwin15.6.0-gcc-ar
gcc7-0.0.9.data/purelib/gcc7/gcc_root/bin/x86_64-apple-darwin15.6.0-gcc-nm
gcc7-0.0.9.data/purelib/gcc7/gcc_root/bin/x86_64-apple-darwin15.6.0-gcc-ranlib
gcc7-0.0.9.data/purelib/gcc7/gcc_root/lib/libatomic.1.dylib
gcc7-0.0.9.data/purelib/gcc7/gcc_root/lib/libatomic.a
gcc7-0.0.9.data/purelib/gcc7/gcc_root/lib/libatomic.dylib
gcc7-0.0.9.data/purelib/gcc7/gcc_root/lib/libatomic.la
gcc7-0.0.9.data/purelib/gcc7/gcc_root/lib/libcc1.0.so
gcc7-0.0.9.data/purelib/gcc7/gcc_root/lib/libcc1.la
gcc7-0.0.9.data/purelib/gcc7/gcc_root/lib/libcc1.so
gcc7-0.0.9.data/purelib/gcc7/gcc_root/lib/libgcc_ext.10.4.dylib
gcc7-0.0.9.data/purelib/gcc7/gcc_root/lib/libgcc_ext.10.5.dylib
gcc7-0.0.9.data/purelib/gcc7/gcc_root/lib/libgcc_s.1.dylib
gcc7-0.0.9.data/purelib/gcc7/gcc_root/lib/libgcc_s_ppc64.1.dylib
gcc7-0.0.9.data/purelib/gcc7/gcc_root/lib/libgcc_s_x86_64.1.dylib
gcc7-0.0.9.data/purelib/gcc7/gcc_root/lib/libgomp.1.dylib
gcc7-0.0.9.data/purelib/gcc7/gcc_root/lib/libgomp.a
gcc7-0.0.9.data/purelib/gcc7/gcc_root/lib/libgomp.dylib
gcc7-0.0.9.data/purelib/gcc7/gcc_root/lib/libgomp.la
gcc7-0.0.9.data/purelib/gcc7/gcc_root/lib/libgomp.spec
gcc7-0.0.9.data/purelib/gcc7/gcc_root/lib/libquadmath.0.dylib
gcc7-0.0.9.data/purelib/gcc7/gcc_root/lib/libquadmath.a
gcc7-0.0.9.dist-info/DESCRIPTION.rst
gcc7-0.0.9.dist-info/METADATA
gcc7-0.0.9.dist-info/RECORD
gcc7-0.0.9.dist-info/WHEEL
gcc7-0.0.9.dist-info/metadata.json
gcc7-0.0.9.dist-info/top_level.txt
